gerritclient/__init__.py
gerritclient/client.py
gerritclient/error.py
gerritclient/main.py
gerritclient/settings.py
gerritclient/commands/__init__.py
gerritclient/commands/account.py
gerritclient/commands/base.py
gerritclient/commands/change.py
gerritclient/commands/group.py
gerritclient/commands/plugin.py
gerritclient/commands/project.py
gerritclient/commands/server.py
gerritclient/common/__init__.py
gerritclient/common/utils.py
gerritclient/tests/__init__.py
gerritclient/tests/conftest.py
gerritclient/tests/unit/__init__.py
gerritclient/tests/unit/test_settings.py
gerritclient/tests/unit/cli/__init__.py
gerritclient/tests/unit/cli/clibase.py
gerritclient/tests/unit/cli/test_account.py
gerritclient/tests/unit/cli/test_change.py
gerritclient/tests/unit/cli/test_group.py
gerritclient/tests/unit/cli/test_plugin.py
gerritclient/tests/unit/cli/test_project.py
gerritclient/tests/unit/cli/test_server.py
gerritclient/tests/unit/common/__init__.py
gerritclient/tests/unit/common/test_utils.py
gerritclient/tests/utils/__init__.py
gerritclient/tests/utils/fake_account.py
gerritclient/tests/utils/fake_change.py
gerritclient/tests/utils/fake_comment.py
gerritclient/tests/utils/fake_commit.py
gerritclient/tests/utils/fake_group.py
gerritclient/tests/utils/fake_plugin.py
gerritclient/tests/utils/fake_project.py
gerritclient/tests/utils/fake_server.py
gerritclient/tests/utils/fake_sshkeyinfo.py
gerritclient/tests/utils/fake_tag.py
gerritclient/tests/utils/fake_weblinkifno.py
gerritclient/v1/__init__.py
gerritclient/v1/account.py
gerritclient/v1/base.py
gerritclient/v1/change.py
gerritclient/v1/group.py
gerritclient/v1/plugin.py
gerritclient/v1/project.py
gerritclient/v1/server.py
python_gerritclient-1.1.0.dist-info/METADATA
python_gerritclient-1.1.0.dist-info/WHEEL
python_gerritclient-1.1.0.dist-info/entry_points.txt
python_gerritclient-1.1.0.dist-info/licenses/AUTHORS
python_gerritclient-1.1.0.dist-info/licenses/LICENSE
python_gerritclient-1.1.0.dist-info/RECORD
