Metadata-Version: 2.4
Name: python-gerritclient
Version: 1.1.0
Summary: CLI tool and Python API wrapper for Gerrit Code Review
Project-URL: Homepage, https://github.com/tivaliy/python-gerritclient
Project-URL: Repository, https://github.com/tivaliy/python-gerritclient
Project-URL: Issues, https://github.com/tivaliy/python-gerritclient/issues
Author-email: Vitalii Kulanov <vitaliy@kulanov.org.ua>
License: Apache-2.0
License-File: AUTHORS
License-File: LICENSE
Keywords: cli,code-review,gerrit,rest-api
Classifier: Environment :: Console
Classifier: Intended Audience :: Information Technology
Classifier: Intended Audience :: System Administrators
Classifier: License :: OSI Approved :: Apache Software License
Classifier: Operating System :: POSIX :: Linux
Classifier: Programming Language :: Python
Classifier: Programming Language :: Python :: 3
Classifier: Programming Language :: Python :: 3.11
Classifier: Programming Language :: Python :: 3.12
Classifier: Programming Language :: Python :: 3.13
Requires-Python: >=3.11
Requires-Dist: cliff>=4.0.0
Requires-Dist: pydantic-settings>=2.0
Requires-Dist: pyyaml>=6.0
Requires-Dist: requests>=2.28.0
Provides-Extra: dev
Requires-Dist: mypy>=1.8.0; extra == 'dev'
Requires-Dist: pytest-cov>=4.1.0; extra == 'dev'
Requires-Dist: pytest>=8.0.0; extra == 'dev'
Requires-Dist: ruff>=0.14.0; extra == 'dev'
Provides-Extra: docs
Requires-Dist: sphinx-rtd-theme>=1.0.0; extra == 'docs'
Requires-Dist: sphinx>=1.6.2; extra == 'docs'
Provides-Extra: test
Requires-Dist: pytest-cov>=4.1.0; extra == 'test'
Requires-Dist: pytest>=8.0.0; extra == 'test'
